antur/__init__.py
antur/__main__.py
antur/antur.tcss
antur/app.py
antur/utils/__init__.py
antur/utils/sitemap_parser.py
antur/widgets/__init__.py
antur/widgets/node_info.py
antur/widgets/search_bar.py
antur/widgets/sitemap_tree.py
antur-0.3.1.dist-info/LICENSE
antur-0.3.1.dist-info/METADATA
antur-0.3.1.dist-info/WHEEL
antur-0.3.1.dist-info/entry_points.txt
antur-0.3.1.dist-info/RECORD
