Metadata-Version: 2.1
Name: antur
Version: 0.3.1
Summary: Antur is a Python TUI tool for browsing and debugging sitemap data.
Home-page: https://github.com/jb3/antur
License: MIT
Keywords: sitemap,xml,tui,cli,debugging,browser
Author: Joe Banks
Author-email: joe@jb3.dev
Requires-Python: >=3.12,<4.0
Classifier: Development Status :: 3 - Alpha
Classifier: Environment :: Console
Classifier: Intended Audience :: Developers
Classifier: License :: OSI Approved :: MIT License
Classifier: Operating System :: OS Independent
Classifier: Programming Language :: Python :: 3
Classifier: Programming Language :: Python :: 3.12
Classifier: Topic :: Internet :: WWW/HTTP
Classifier: Topic :: Internet :: WWW/HTTP :: Indexing/Search
Classifier: Topic :: Internet :: WWW/HTTP :: Site Management
Classifier: Topic :: Utilities
Requires-Dist: aiohttp (>=3.9.5,<4.0.0)
Requires-Dist: humanize (>=4.10.0,<5.0.0)
Requires-Dist: lxml (>=5.2.1,<6.0.0)
Requires-Dist: textual (>=0.71.0,<0.72.0)
Project-URL: Repository, https://github.com/jb3/antur
